odoo/addons/stock_lot_multi_image/README.rst
odoo/addons/stock_lot_multi_image/__init__.py
odoo/addons/stock_lot_multi_image/__manifest__.py
odoo/addons/stock_lot_multi_image/i18n/it.po
odoo/addons/stock_lot_multi_image/i18n/stock_lot_multi_image.pot
odoo/addons/stock_lot_multi_image/models/__init__.py
odoo/addons/stock_lot_multi_image/models/stock_lot.py
odoo/addons/stock_lot_multi_image/readme/CONTEXT.md
odoo/addons/stock_lot_multi_image/readme/DESCRIPTION.md
odoo/addons/stock_lot_multi_image/readme/USAGE.md
odoo/addons/stock_lot_multi_image/static/description/icon.png
odoo/addons/stock_lot_multi_image/static/description/index.html
odoo/addons/stock_lot_multi_image/static/description/usage.png
odoo/addons/stock_lot_multi_image/views/stock_lot_view.xml
odoo_addon_stock_lot_multi_image-16.0.1.0.0.4.dist-info/METADATA
odoo_addon_stock_lot_multi_image-16.0.1.0.0.4.dist-info/WHEEL
odoo_addon_stock_lot_multi_image-16.0.1.0.0.4.dist-info/top_level.txt
odoo_addon_stock_lot_multi_image-16.0.1.0.0.4.dist-info/RECORD
